MANIFEST.in
setup.cfg
setup.py
src/sbin/tmscli
src/themis/AI.py
src/themis/__init__.py
src/themis/group.py
src/themis/marshalredis.py
src/themis/policy.py
src/themis/ratelimiter.py
src/themis/static.py
src/themis/utils.py
themis_core.egg-info/PKG-INFO
themis_core.egg-info/SOURCES.txt
themis_core.egg-info/dependency_links.txt
themis_core.egg-info/requires.txt
themis_core.egg-info/top_level.txt