Metadata-Version: 1.0
Name: themis-core
Version: 0.1
Summary: Core themis library
Home-page: https://github.com/sandromello/themis-py
Author: Sandro Mello
Author-email: sandromll@gmail.com
License: UNKNOWN
Platform: UNKNOWN
